ipyuploads/__init__.py
ipyuploads/_version.py
ipyuploads/cleartext.py
ipyuploads/upload.py
ipyuploads/labextension/package.json
ipyuploads/labextension/static/261.1e9affb0af66da32d7b0.js
ipyuploads/labextension/static/486.85169b55bcec15cb44f6.js
ipyuploads/labextension/static/486.85169b55bcec15cb44f6.js.LICENSE.txt
ipyuploads/labextension/static/568.cf24dc678ceb0c3e209a.js
ipyuploads/labextension/static/remoteEntry.0f2cc1da9f6b13905794.js
ipyuploads/labextension/static/style.js
ipyuploads/labextension/static/third-party-licenses.json
ipyuploads/nbextension/extension.js
ipyuploads/nbextension/index.js
ipyuploads/nbextension/index.js.LICENSE.txt
ipyuploads-0.2.4.data/data/share/jupyter/labextensions/@g2nb/ipyuploads/package.json
ipyuploads-0.2.4.data/data/share/jupyter/labextensions/@g2nb/ipyuploads/static/261.1e9affb0af66da32d7b0.js
ipyuploads-0.2.4.data/data/share/jupyter/labextensions/@g2nb/ipyuploads/static/486.85169b55bcec15cb44f6.js
ipyuploads-0.2.4.data/data/share/jupyter/labextensions/@g2nb/ipyuploads/static/486.85169b55bcec15cb44f6.js.LICENSE.txt
ipyuploads-0.2.4.data/data/share/jupyter/labextensions/@g2nb/ipyuploads/static/568.cf24dc678ceb0c3e209a.js
ipyuploads-0.2.4.data/data/share/jupyter/labextensions/@g2nb/ipyuploads/static/remoteEntry.0f2cc1da9f6b13905794.js
ipyuploads-0.2.4.data/data/share/jupyter/labextensions/@g2nb/ipyuploads/static/style.js
ipyuploads-0.2.4.data/data/share/jupyter/labextensions/@g2nb/ipyuploads/static/third-party-licenses.json
ipyuploads-0.2.4.data/data/share/jupyter/labextensions/@g2nb/ipyuploads/install.json
ipyuploads-0.2.4.dist-info/METADATA
ipyuploads-0.2.4.dist-info/WHEEL
ipyuploads-0.2.4.dist-info/licenses/LICENSE
ipyuploads-0.2.4.dist-info/RECORD
