Metadata-Version: 2.3
Name: ipyuploads
Version: 0.2.4
Summary: A Jupyter file widget with chunked upload capabilities
Project-URL: Homepage, https://github.com/g2nb/ipyuploads
Author-email: Thorin Tabor <tmtabor@cloud.ucsd.edu>
License: BSD 3-Clause License
License-File: LICENSE
Keywords: ipython,jupyter,widgets
Classifier: Development Status :: 4 - Beta
Classifier: Framework :: IPython
Classifier: Intended Audience :: Developers
Classifier: Intended Audience :: Science/Research
Classifier: Programming Language :: Python :: 3.6
Classifier: Programming Language :: Python :: 3.7
Classifier: Programming Language :: Python :: 3.8
Classifier: Programming Language :: Python :: 3.9
Classifier: Topic :: Multimedia :: Graphics
Requires-Python: >=3.6
Requires-Dist: ipywidgets<9,>=7
